.gitignore
.project
.pydevproject
LICENSE
README.md
setup.py
mediatumbabel/__init__.py
mediatumbabel.egg-info/PKG-INFO
mediatumbabel.egg-info/SOURCES.txt
mediatumbabel.egg-info/dependency_links.txt
mediatumbabel.egg-info/pbr.json
mediatumbabel.egg-info/requires.txt
mediatumbabel.egg-info/top_level.txt
tests/babel.cfg
tests/fixtures.py
tests/test_formatting.py
tests/test_gettext.py
tests/translations/messages.pot
tests/translations/de/LC_MESSAGES/messages.mo
tests/translations/de/LC_MESSAGES/messages.po
tests/translations2/de_AT/LC_MESSAGES/messages.mo