Metadata-Version: 1.1
Name: mediatumbabel
Version: 0.1.1
Summary: flask-babel port to provide i18n for mediaTUM (+jinja2) with some improvements
Home-page: https://mediatumdev.ub.tum.de/projects/mediatum-babel
Author: Tobias Stenzel
Author-email: tobias.stenzel@tum.de
License: GNU General Public License v3 (GPLv3)
Keywords: babel i18n pybabel mediatum
Platform: UNKNOWN
Classifier: Development Status :: 3 - Alpha
Classifier: Intended Audience :: Developers
Classifier: License :: OSI Approved :: GNU General Public License v3 (GPLv3)
Classifier: Programming Language :: Python :: 2
Classifier: Programming Language :: Python :: 2.7
Classifier: Topic :: Database
